setup.py
tinycm_vim/__init__.py
tinycm_vim.egg-info/PKG-INFO
tinycm_vim.egg-info/SOURCES.txt
tinycm_vim.egg-info/dependency_links.txt
tinycm_vim.egg-info/requires.txt
tinycm_vim.egg-info/top_level.txt