Metadata-Version: 1.1
Name: tinycm-vim
Version: 0.1.4
Summary: VIM definition for TinyCM
Home-page: https://github.com/MartijnBraam/TinyCM
Author: Martijn Braam
Author-email: martijn@brixit.nl
License: MIT
Keywords: configuration management,puppet
Platform: UNKNOWN
Classifier: Programming Language :: Python
Classifier: Programming Language :: Python :: 3
Classifier: Development Status :: 4 - Beta
Classifier: Operating System :: POSIX :: Linux
Classifier: License :: OSI Approved :: MIT License
